pywebhk/__init__.py
pywebhk/embed.py
pywebhk/webhook.py
pywebhk/ext/__init__.py
pywebhk/ext/errors.py
pywebhk/ext/url.py
pywebhk-1.0.5.dist-info/LICENSE
pywebhk-1.0.5.dist-info/METADATA
pywebhk-1.0.5.dist-info/WHEEL
pywebhk-1.0.5.dist-info/top_level.txt
pywebhk-1.0.5.dist-info/RECORD
